vitalx/types/__init__.py
vitalx/types/billing.py
vitalx/types/environments.py
vitalx/types/geo.py
vitalx/types/providers.py
vitalx/types/query.py
vitalx/types/resources.py
vitalx_types-0.3.0.dist-info/WHEEL
vitalx_types-0.3.0.dist-info/LICENSE.txt
vitalx_types-0.3.0.dist-info/METADATA
vitalx_types-0.3.0.dist-info/RECORD
