Metadata-Version: 2.1
Name: vitalx-types
Version: 0.3.0
Summary: Vital Horizon AI common types package
Home-page: https://www.tryvital.com/
License: AGPL-3.0-only
Author: Vital
Author-email: developers@tryvital.io
Requires-Python: >=3.11,<4.0
Classifier: Development Status :: 4 - Beta
Classifier: Intended Audience :: Developers
Classifier: Intended Audience :: Science/Research
Classifier: License :: OSI Approved :: GNU Affero General Public License v3
Classifier: Programming Language :: Python :: 3
Classifier: Programming Language :: Python :: 3.11
Classifier: Topic :: Scientific/Engineering
Classifier: Topic :: Scientific/Engineering :: Artificial Intelligence
Classifier: Topic :: Software Development
Project-URL: Documentation, https://docs.tryvital.io/
